{
  "section_number": "420",
  "section_title": "Cheating and dishonestly inducing delivery of property",
  "file_id": "section-420",
  "chapter_number": "17",
  "chapter_title": "Of Offences Against Property",
  "act_code": "ipc",
  "act_name": "Indian Penal Code",
  "act_year": "1860",
  "text": "Whoever cheats and thereby dishonestly induces the person deceived to deliver any property to any person, or to make, alter or destroy the whole or any part of a valuable security, or anything which is signed or sealed, and which is capable of being converted into a valuable security, shall be punished with imprisonment of either description for a term which may extend to seven years, and shall also be liable to fine.",
  "explanations": [],
  "amendments": [],
  "source_url": "https://devgan.in/ipc/chapter_17.php"
}