{
  "section_number": "437",
  "section_title": "Mischief with intent to destroy or make unsafe a decked vessel or one of twenty tons burden",
  "file_id": "section-437",
  "chapter_number": "17",
  "chapter_title": "Of Offences Against Property",
  "act_code": "ipc",
  "act_name": "Indian Penal Code",
  "act_year": "1860",
  "text": "Whoever commits mischief to any decked vessel or any vessel of a burden of twenty tons or upwards, intending to destroy or render unsafe, or knowing it to be likely that he will thereby destroy or render unsafe, that vessel, shall be punished with imprisonment of either description for a term which may extend to ten years, and shall also be liable to fine.",
  "explanations": [],
  "amendments": [],
  "source_url": "https://devgan.in/ipc/chapter_17.php"
}