{
  "section_number": "63",
  "section_title": "Property attached in execution of decrees of several Courts",
  "file_id": "section-63",
  "chapter_number": "02",
  "chapter_title": "Part II – Execution",
  "act_code": "cpc",
  "act_name": "Code of Civil Procedure",
  "act_year": "1908",
  "text": "Where property not in the custody of any Court is under attachment in execution of decrees of more Courts than one, the Court which shall receive or realize such property and shall determine any claim thereto any objection to the attachment thereof shall be the Court of highest grade, or, where there is no difference in grade between such Courts, the Court under whose decree the property was first attached. \n Nothing in this section shall be deemed to invalidate any proceeding taken by a Court executing one of such decrees. \n Explanation – For the purposes of sub-section (2), “proceeding taken by a Court” does not include an order allowing, to a decree-holder who has purchased property at a sale held in execution of a decree, set off to the extent of the purchase price payable by him.",
  "explanations": [],
  "amendments": [],
  "source_url": "https://devgan.in/cpc/chapter_02.php"
}