{
  "section_number": "3",
  "section_title": "Necessity for driving license",
  "file_id": "section-3",
  "chapter_number": "02",
  "chapter_title": "Licensing of Drivers of Motor Vehicles",
  "act_code": "mva",
  "act_name": "Motor Vehicles Act",
  "act_year": "1988",
  "text": "No person shall drive a motor vehicle in any public place unless he holds an effective driving license issued to him authorising him to drive the vehicle; and no person shall so drive a transport vehicle other than a motor cab or motor cycle hired for his own use or rented under any scheme made under sub-section (2) of section 75 unless his driving license specifically entitles him so to do. \n The conditions subject to which sub-section (1) shall not apply to a person receiving instructions in driving a motor vehicle shall be such as may be prescribed by the Central Government.",
  "explanations": [],
  "amendments": [],
  "source_url": "https://devgan.in/mva/chapter_02.php"
}