{
  "section_number": "16",
  "section_title": "Revocation of driving license on grounds of disease or disability",
  "file_id": "section-16",
  "chapter_number": "02",
  "chapter_title": "Licensing of Drivers of Motor Vehicles",
  "act_code": "mva",
  "act_name": "Motor Vehicles Act",
  "act_year": "1988",
  "text": "Notwithstanding anything contained in the foregoing sections, any licensing authority may at any time revoke a driving license or may require, as a condition of continuing to hold such driving license, the holder thereof to produce a medical certificate in the same form and in the same manner as is referred to in sub-section (3) of section 8, if the licensing authority has reasonable grounds to believe that the holder of the driving license is, by virtue of any disease or disability, unfit to drive a motor vehicle and where the authority revoking a driving license is not the authority which issued the same, it shall intimate the fact of revocation to the authority which issued that license.",
  "explanations": [],
  "amendments": [],
  "source_url": "https://devgan.in/mva/chapter_02.php"
}