{
  "section_number": "54",
  "section_title": "Cancellation of registration suspended under section 53",
  "file_id": "section-54",
  "chapter_number": "04",
  "chapter_title": "Registration of Motor Vehicles",
  "act_code": "mva",
  "act_name": "Motor Vehicles Act",
  "act_year": "1988",
  "text": "Where the suspension of registration of a vehicle under section 53 has continued without interruption for a period of not less than six months, the registering authority within whose jurisdiction the vehicle was when the registration was suspended, may, if it is the original registering authority, cancel the registration, and if it is not the original registering authority, shall forward the certificate of registration to that authority which may cancel the registration.",
  "explanations": [],
  "amendments": [],
  "source_url": "https://devgan.in/mva/chapter_04.php"
}