{
  "section_number": "40",
  "section_title": "Discharge of indorser’s liability",
  "file_id": "section-40",
  "chapter_number": "03",
  "chapter_title": "Parties to Notes, Bills and Cheques",
  "act_code": "nia",
  "act_name": "National Investigation Agency Act",
  "act_year": "2008",
  "text": "Where the holder of a negotiable instrument, without the consent of the indorser, destroys or impairs the indorser’s remedy against a prior party, the indorser is discharged from liability to the holder to the same extent as if the instrument had been paid at maturity. Illustrations \n A is the holder of a bill of exchange made payable to the order of B, which contains the following indorsements in blank: \n First indorsement, “B.” \n Second indorsement, “Peter Williams.” \n Third indorsement, “Wright & Co.” \n Fourth indorsement, “John Rozario.” \n This bill A puts in suit against John Rozario and strikes out, without John Rozario’s consent, the indorsements by Peter Williams and Wright & Co. A is not entitled to recover anything from John Rozario.",
  "explanations": [],
  "amendments": [],
  "source_url": "https://devgan.in/nia/chapter_03.php"
}