{
  "section_number": "46",
  "section_title": "Delivery",
  "file_id": "section-46",
  "chapter_number": "04",
  "chapter_title": "Of Negotiation",
  "act_code": "nia",
  "act_name": "National Investigation Agency Act",
  "act_year": "2008",
  "text": "The making, acceptance or indorsement of a promissory note, bill of exchange or cheque is completed by delivery, actual or constructive. \n As between parties standing in immediate relation, delivery to be effectual must be made by the party making, accepting or indorsing the instrument, or by a person authorized by him in that behalf. \n As between such parties and any holder of the instrument other than a holder in due course, it may be shown that the instrument was delivered conditionally or for a special purpose only, and not for the purpose of transferring absolutely the property therein. \n A promissory note, bill of exchange or cheque payable to bearer is negotiable by the delivery thereof. \n A promissory note, bill of exchange or cheque payable to order is negotiable by the holder by indorsement and delivery thereof.",
  "explanations": [],
  "amendments": [],
  "source_url": "https://devgan.in/nia/chapter_04.php"
}