{
  "section_number": "352",
  "section_title": "Certain Judges and Magistrates not to try certain offences when committed before themselves",
  "file_id": "section-352",
  "chapter_number": "26",
  "chapter_title": "Provisions As To Offences Affecting The Administration Of Justice",
  "act_code": "crpc",
  "act_name": "Code of Criminal Procedure",
  "act_year": "1973",
  "text": "Except as provided in sections 344, 345, 349 and 350, no Judge of a Criminal Court (other than a Judge of a High Court) or Magistrate shall try any person for any offence referred to in section 195, when such offence is committed before himself or in contempt of his authority, or is brought under his notice as such judge or magistrate in the course of a judicial proceeding.",
  "explanations": [],
  "amendments": [],
  "source_url": "https://devgan.in/crpc/chapter_26.php"
}