{
  "section_number": "324",
  "section_title": "Trial of persons previously convicted of offences against coinage, stamp law or property",
  "file_id": "section-324",
  "chapter_number": "24",
  "chapter_title": "General Provisions As To Inquiries And Trials",
  "act_code": "crpc",
  "act_name": "Code of Criminal Procedure",
  "act_year": "1973",
  "text": "Where a person, having been convicted of an offence punishable under Chapter XII or Chapter XVII of the Indian Penal Code (45 of 1860) with imprisonment for a term of three years or upwards, is again accused of any offence punishable under either of those Chapters with imprisonment for a term of three years or upwards, and the Magistrate before whom the case is pending is satisfied that there is ground for presuming that such person has committed the offence, he shall be sent for trial to the Chief Judicial Magistrate or committed to the Court of Session, unless the Magistrate is competent to try the case and is of opinion that he can himself pass and adequate sentence if the accused is convicted. \n When any person is sent for trial to the Chief Judicial Magistrate or committed to the Court of Session under Sub-Section (1) any other person accused jointly with him in the same inquiry or trial shall be similarly sent or committed, unless the Magistrate discharges such other person under section 239 or section 245, as the case may be.",
  "explanations": [],
  "amendments": [],
  "source_url": "https://devgan.in/crpc/chapter_24.php"
}