{
  "section_number": "276",
  "section_title": "Record in trial before Court of Session",
  "file_id": "section-276",
  "chapter_number": "23",
  "chapter_title": "Evidence In Inquiries And Trials",
  "act_code": "crpc",
  "act_name": "Code of Criminal Procedure",
  "act_year": "1973",
  "text": "In all trials before a Court of Session, the evidence of each witness shall, as his examination proceeds, be taken down in writing either by the presiding Judge himself or by his dictation in open Court or under his direction and superintendence, by an officer of the Court appointed by him in this behalf. \n Such evidence shall ordinarily be taken down in the form of a narrative, but the presiding Judge may, in his discretion take down or cause to be taken down, any part of such evidence in the form of question and answer. \n The evidence so taken down shall be signed by the presiding Judge and shall form part of the record.",
  "explanations": [],
  "amendments": [],
  "source_url": "https://devgan.in/crpc/chapter_23.php"
}