{
  "section_number": "312",
  "section_title": "Attempt to commit robbery or dacoity when armed with deadly weapon.",
  "file_id": "section-312",
  "chapter_number": "17",
  "chapter_title": "Of Offences Against Property",
  "act_code": "bns",
  "act_name": "Bharatiya Nyaya Sanhita",
  "act_year": "2023",
  "text": "If, at the time of attempting to commit robbery or dacoity, the offender is armed with any deadly weapon, the imprisonment with which such offender shall be punished shall not be less than seven years. \n BNSS Classification \n Imprisonment for not less than 7 years. \n Cognizable \n Non-bailable \n Triable by Court of Session.",
  "explanations": [],
  "amendments": [],
  "source_url": "https://devgan.in/bns/chapter_17.php"
}