{
  "section_number": "113",
  "section_title": "Proof of cession of territory",
  "file_id": "section-113",
  "chapter_number": "07",
  "chapter_title": "Of the Burden of Proof",
  "act_code": "iea",
  "act_name": "Indian Evidence Act",
  "act_year": "1872",
  "text": "A notification in the Official Gazette that any portion of British territory has before the commencement of Part III of the Government of India Act, 1935 (26 Geo. 5, ch. 2) been ceded to any Native State, Prince or Ruler, shall be conclusive proof that a valid cession of such territory took place at the dale mentioned in such notification",
  "explanations": [],
  "amendments": [],
  "source_url": "https://devgan.in/iea/chapter_07.php"
}