{
  "section_number": "88A",
  "section_title": "Presumption as to electronic messages",
  "file_id": "section-88a",
  "chapter_number": "05",
  "chapter_title": "Of Documentary Evidence",
  "act_code": "iea",
  "act_name": "Indian Evidence Act",
  "act_year": "1872",
  "text": "The Court may presume that an electronic message, forwarded by the originator through an electronic mail server to the addressee to whom the message purports to be addressed corresponds with the message as fed into his computer for transmission; but the Court shall not make any presumption as to the person by whom such message was sent. \n Explanations \n For the purposes of this section, the expressions addressee and originator shall have the same meanings respectively assigned to them in clauses (b) and (za) of sub-section (1) of section 2 of the Information Technology Act, 2000.",
  "explanations": [],
  "amendments": [],
  "source_url": "https://devgan.in/iea/chapter_05.php"
}