{
  "section_number": "76",
  "section_title": "Certified copies of public documents",
  "file_id": "section-76",
  "chapter_number": "05",
  "chapter_title": "Of Documentary Evidence",
  "act_code": "iea",
  "act_name": "Indian Evidence Act",
  "act_year": "1872",
  "text": "Every public officer having the custody of a public document, which any person has a right to inspect, shall give that person on demand a copy of it on payment of the legal fees therefore, together with a certificate written at the foot of such copy that it is true copy of such document or part thereof, as the case may be and such certificate shall be dated and subscribed by such officer with his name and his official title, and shall be sealed, whenever such officer is authorised by law to make use of a seal; and such copies so certified shall be called certified copies. \n Explanations \n Any officer who, by the ordinary course of official duty, is authorized to deliver such copies, shall be deemed to have the custody of such documents within the meaning of this section. \n 1. A village-officer in the Punjab has been declared for the purposes of this Act to be a public officer having the custody of a public document-see the Punjab Land Revenue Act, 1887 (17 of 1887), section, 151 (2).",
  "explanations": [],
  "amendments": [],
  "source_url": "https://devgan.in/iea/chapter_05.php"
}